pysimpledab.py
pysimpledab-1.1.dist-info/LICENSE.txt
pysimpledab-1.1.dist-info/METADATA
pysimpledab-1.1.dist-info/WHEEL
pysimpledab-1.1.dist-info/top_level.txt
pysimpledab-1.1.dist-info/RECORD
