Metadata-Version: 2.1
Name: pysimpledab
Version: 1.1
Summary: This is a ctypes python wrapper around simple_dab
Author: 1337Misom
License: GNU GENERAL PUBLIC LICENSE
Project-URL: Homepage, https://gitlab.com/1337Misom/pysimpledab
Classifier: Development Status :: 3 - Alpha
Classifier: Programming Language :: Python :: 3
Classifier: License :: OSI Approved :: GNU General Public License v3 (GPLv3)
Classifier: Intended Audience :: Developers
Requires-Python: >=3.10
License-File: LICENSE.txt
